bridges/__init__.py
bridges/array.py
bridges/array1d.py
bridges/array2d.py
bridges/array3d.py
bridges/audio_channel.py
bridges/audio_clip.py
bridges/avl_tree_element.py
bridges/bar_chart.py
bridges/bfs_benchmark.py
bridges/bin_tree_element.py
bridges/blocking_game.py
bridges/bridges.py
bridges/bst_element.py
bridges/camera.py
bridges/circ_dl_element.py
bridges/circ_sl_element.py
bridges/circle.py
bridges/color.py
bridges/color_grid.py
bridges/connector.py
bridges/dl_element.py
bridges/edge.py
bridges/element.py
bridges/element_visualizer.py
bridges/game_cell.py
bridges/game_grid.py
bridges/gamebase.py
bridges/gamebase3D.py
bridges/graph_adj_list.py
bridges/graph_adj_matrix.py
bridges/graph_benchmark.py
bridges/grid.py
bridges/input_helper.py
bridges/input_state_machine.py
bridges/kd_tree_element.py
bridges/keypress_listener.py
bridges/label.py
bridges/light.py
bridges/line_chart.py
bridges/link_visualizer.py
bridges/map.py
bridges/mesh.py
bridges/ml_element.py
bridges/named_color.py
bridges/named_symbol.py
bridges/non_blocking_game.py
bridges/non_blocking_game3D.py
bridges/page_rank_benchmark.py
bridges/particle_system.py
bridges/polygon.py
bridges/polyline.py
bridges/primitives.py
bridges/rectangle.py
bridges/scene.py
bridges/shortest_path_benchmark.py
bridges/sl_element.py
bridges/socket_connection.py
bridges/sorting_benchmark.py
bridges/symbol.py
bridges/symbol_collection.py
bridges/symbol_group.py
bridges/text.py
bridges/tree_element.py
bridges/us_map.py
bridges/world_map.py
bridges/data_src_dependent/__init__.py
bridges/data_src_dependent/actor_movie_imdb.py
bridges/data_src_dependent/amenity.py
bridges/data_src_dependent/book.py
bridges/data_src_dependent/cancer_incidence.py
bridges/data_src_dependent/city.py
bridges/data_src_dependent/country.py
bridges/data_src_dependent/data_source.py
bridges/data_src_dependent/earthquake_usgs.py
bridges/data_src_dependent/elevation.py
bridges/data_src_dependent/game.py
bridges/data_src_dependent/gutenberg_book.py
bridges-3.5.0.dist-info/METADATA
bridges-3.5.0.dist-info/WHEEL
bridges-3.5.0.dist-info/top_level.txt
bridges-3.5.0.dist-info/RECORD
