Metadata-Version: 2.1
Name: bridges
Version: 3.5.0
Summary: Bridging Real-world Infrastructure Designed to Goal-align, Engage, and Stimulate, an NSF TUES
Home-page: https://github.com/BridgesUNCC/bridges-python
Author: BRIDGES
Author-email: bridges.uncc@gmail.com
Classifier: Programming Language :: Python :: 3
Classifier: License :: OSI Approved :: MIT License
Classifier: Operating System :: OS Independent
Requires-Python: >3.5.2
Requires-Dist: SPARQLWrapper (>=1.8.4)
Requires-Dist: python-socketio[client] (>=4.3.0)
Requires-Dist: requests (>=2.21.0)
Requires-Dist: webcolors (>=1.8.1)
